wigglerapi/__init__.py
wigglerapi/cli.py
wigglerapi/main.py
wigglerapi-0.0.10.dist-info/METADATA
wigglerapi-0.0.10.dist-info/WHEEL
wigglerapi-0.0.10.dist-info/entry_points.txt
wigglerapi-0.0.10.dist-info/top_level.txt
wigglerapi-0.0.10.dist-info/RECORD
